openbb_provider/__init__.py
openbb_provider/abstract/__init__.py
openbb_provider/abstract/data.py
openbb_provider/abstract/fetcher.py
openbb_provider/abstract/provider.py
openbb_provider/abstract/query_params.py
openbb_provider/py.typed
openbb_provider/query_executor.py
openbb_provider/registry.py
openbb_provider/registry_map.py
openbb_provider/standard_models/__init__.py
openbb_provider/standard_models/ameribor_rates.py
openbb_provider/standard_models/analyst_estimates.py
openbb_provider/standard_models/available_indices.py
openbb_provider/standard_models/balance_of_payments.py
openbb_provider/standard_models/balance_sheet.py
openbb_provider/standard_models/balance_sheet_growth.py
openbb_provider/standard_models/bond_prices.py
openbb_provider/standard_models/bond_reference.py
openbb_provider/standard_models/bond_trades.py
openbb_provider/standard_models/calendar_dividend.py
openbb_provider/standard_models/calendar_earnings.py
openbb_provider/standard_models/calendar_ipo.py
openbb_provider/standard_models/calendar_splits.py
openbb_provider/standard_models/cash_flow.py
openbb_provider/standard_models/cash_flow_growth.py
openbb_provider/standard_models/company_filings.py
openbb_provider/standard_models/company_news.py
openbb_provider/standard_models/company_overview.py
openbb_provider/standard_models/cot.py
openbb_provider/standard_models/cot_search.py
openbb_provider/standard_models/cp.py
openbb_provider/standard_models/cpi.py
openbb_provider/standard_models/crypto_historical.py
openbb_provider/standard_models/crypto_search.py
openbb_provider/standard_models/currency_historical.py
openbb_provider/standard_models/currency_pairs.py
openbb_provider/standard_models/currency_reference_rates.py
openbb_provider/standard_models/dwpcr_rates.py
openbb_provider/standard_models/earnings_call_transcript.py
openbb_provider/standard_models/ecb_interest_rates.py
openbb_provider/standard_models/economic_calendar.py
openbb_provider/standard_models/equity_ftd.py
openbb_provider-1.0.0b1.dist-info/METADATA
openbb_provider-1.0.0b1.dist-info/WHEEL
openbb_provider-1.0.0b1.dist-info/RECORD
