Metadata-Version: 2.1
Name: openbb-provider
Version: 1.0.0b1
Summary: OpenBB package to execute queries to financial data providers
Author: OpenBB Team
Author-email: hello@openbb.co
Requires-Python: >=3.8,<4.0
Classifier: Programming Language :: Python :: 3
Classifier: Programming Language :: Python :: 3.8
Classifier: Programming Language :: Python :: 3.9
Classifier: Programming Language :: Python :: 3.10
Classifier: Programming Language :: Python :: 3.11
Classifier: Programming Language :: Python :: 3.12
Requires-Dist: importlib-metadata (>=6.8.0,<7.0.0)
Requires-Dist: importlib_metadata (>=6.8.0,<7.0.0)
Requires-Dist: pydantic (>=2.5.1,<3.0.0)
Requires-Dist: python-dotenv (>=1.0.0,<2.0.0)
Requires-Dist: requests (>=2.31.0,<3.0.0)
